multiflexi_client/__init__.py
multiflexi_client/api_client.py
multiflexi_client/api_response.py
multiflexi_client/configuration.py
multiflexi_client/exceptions.py
multiflexi_client/py.typed
multiflexi_client/rest.py
multiflexi_client/api/__init__.py
multiflexi_client/api/app_api.py
multiflexi_client/api/company_api.py
multiflexi_client/api/default_api.py
multiflexi_client/api/gdpr_api.py
multiflexi_client/api/job_api.py
multiflexi_client/api/runtemplate_api.py
multiflexi_client/api/user_api.py
multiflexi_client/models/__init__.py
multiflexi_client/models/app.py
multiflexi_client/models/app_environment_value.py
multiflexi_client/models/app_exit_codes_inner.py
multiflexi_client/models/company.py
multiflexi_client/models/conf_field.py
multiflexi_client/models/configuration.py
multiflexi_client/models/credential.py
multiflexi_client/models/credential_type.py
multiflexi_client/models/customer.py
multiflexi_client/models/data_export_data.py
multiflexi_client/models/data_export_data_activity_logs_inner.py
multiflexi_client/models/data_export_data_audit_trails.py
multiflexi_client/models/data_export_data_audit_trails_data_export_requests_inner.py
multiflexi_client/models/data_export_data_company_associations_inner.py
multiflexi_client/models/data_export_data_consent_records.py
multiflexi_client/models/data_export_data_consent_records_consent_audit_trail_inner.py
multiflexi_client/models/data_export_data_consent_records_consent_records_inner.py
multiflexi_client/models/data_export_data_credentials_inner.py
multiflexi_client/models/data_export_data_export_metadata.py
multiflexi_client/models/data_export_data_job_history_inner.py
multiflexi_client/models/data_export_data_session_history.py
multiflexi_client/models/data_export_data_session_history_current_session_info.py
multiflexi_client/models/data_export_data_user_profile.py
multiflexi_client/models/data_export_response.py
multiflexi_client/models/data_export_status_response.py
multiflexi_client-1.1.0.dist-info/METADATA
multiflexi_client-1.1.0.dist-info/WHEEL
multiflexi_client-1.1.0.dist-info/top_level.txt
multiflexi_client-1.1.0.dist-info/RECORD
