Metadata-Version: 2.4
Name: multiflexi_client
Version: 1.1.0
Summary: MultiFlexi API
Home-page: https://github.com/VitexSoftware/multiflexi-api-python-client
Author: OpenAPI Generator community
Author-email: OpenAPI Generator Community <team@openapitools.org>
License: MIT
Project-URL: Repository, https://github.com/VitexSoftware/python-multiflexi
Keywords: OpenAPI,OpenAPI-Generator,MultiFlexi API
Requires-Python: >=3.9
Requires-Dist: urllib3<3.0.0,>=2.1.0
Requires-Dist: python-dateutil>=2.8.2
Requires-Dist: pydantic>=2
Requires-Dist: typing-extensions>=4.7.1
Dynamic: author
Dynamic: home-page
